pymodoro_cli.py
pymodoro_cli-0.2.0.dist-info/entry_points.txt
pymodoro_cli-0.2.0.dist-info/METADATA
pymodoro_cli-0.2.0.dist-info/WHEEL
pymodoro_cli-0.2.0.dist-info/RECORD
