Metadata-Version: 2.1
Name: pymodoro-cli
Version: 0.2.0
Summary: 
Author: withpouriya
Author-email: pouriya.raj@gmail.com
Requires-Python: >=3.11,<4.0
Classifier: Programming Language :: Python :: 3
Classifier: Programming Language :: Python :: 3.11
Requires-Dist: colr (==0.9.1)
Requires-Dist: pygame (==2.5.0)
